modlee/__init__.py
modlee/api_client.py
modlee/config.py
modlee/data_stats.py
modlee/dev_data.py
modlee/model_text_converter.py
modlee/modlee_image_model.py
modlee/modlee_model.py
modlee/rep.py
modlee/retriever.py
modlee/utils.py
archee-0.0.1.post5.dist-info/METADATA
archee-0.0.1.post5.dist-info/WHEEL
archee-0.0.1.post5.dist-info/top_level.txt
archee-0.0.1.post5.dist-info/RECORD
