Metadata-Version: 2.1
Name: archee
Version: 0.0.1.post5
Summary: modlee package
Author-email: modlee <michael@modlee.ai>
Requires-Python: >=3.10
Requires-Dist: lightning ==2.0.7
Requires-Dist: mlflow ==2.6.0
Requires-Dist: numpy
Requires-Dist: pydantic ==1.10.12
Requires-Dist: pytorch-lightning ==2.0.7
Requires-Dist: scikit-learn ==1.3.0
Requires-Dist: scipy ==1.11.1
Requires-Dist: setuptools ==68.0.0
Requires-Dist: torch ==2.0.1
Requires-Dist: torchmetrics >=1.0.0
Requires-Dist: torchvision >=0.15.2
